<?xml version="1.0" encoding="UTF-8"?>
<persistence version="2.0" xmlns="http://java.sun.com/xml/ns/persistence" xmlns:xsi="http://www.w3.org/2001/XMLSchema-instance" xsi:schemaLocation="http://java.sun.com/xml/ns/persistence http://java.sun.com/xml/ns/persistence/persistence_2_0.xsd">
    <persistence-unit name="bus-data">
        <class>com.spring.entities.CheDo</class>
        <class>com.spring.entities.ChuyenXe</class>
        <class>com.spring.entities.GiaVeLuot</class>
        <class>com.spring.entities.GiaVeThang</class>
        <class>com.spring.entities.KhachThang</class>
        <class>com.spring.entities.NhanVien</class>
        <class>com.spring.entities.Role</class>
        <class>com.spring.entities.TaiKhoan</class>
        <class>com.spring.entities.ThongTinVeLuot</class>
        <class>com.spring.entities.ThongTinVeThang</class>
        <class>com.spring.entities.TuyenXe</class>
        <class>com.spring.entities.Xe</class>
    </persistence-unit>
</persistence>